setup.py
qiniu_upload.egg-info/PKG-INFO
qiniu_upload.egg-info/SOURCES.txt
qiniu_upload.egg-info/dependency_links.txt
qiniu_upload.egg-info/entry_points.txt
qiniu_upload.egg-info/requires.txt
qiniu_upload.egg-info/top_level.txt
qiniuupload/__init__.py
qiniuupload/cli.py
qiniuupload/common.py
qiniuupload/config.py
qiniuupload/remove.py
qiniuupload/upload.py