Metadata-Version: 1.1
Name: qiniu-upload
Version: 0.1.3
Summary: A simple tool makes us easier upload files to Qiniu Resource (Cloud) Storage
Home-page: https://github.com/NanJingBoy/qiniu_upload
Author: Tom.Huang
Author-email: hzlhu.dargon@gmail.com
License: MIT
Platform: any
Classifier: Intended Audience :: End Users/Desktop
Classifier: License :: OSI Approved :: MIT License
Classifier: Operating System :: OS Independent
Classifier: Programming Language :: Python
Classifier: Programming Language :: Python :: 2
Classifier: Programming Language :: Python :: 2.6
Classifier: Programming Language :: Python :: 2.7
Classifier: Topic :: Internet :: WWW/HTTP :: Dynamic Content
Classifier: Topic :: Software Development :: Libraries :: Python Modules
